test.py
bitblock/__init__.py
bitblock/_util.py
bitblock/rpc/__init__.py
bitblock/rpc/_exceptions.py
bitblock/rpc/_types.py
bitblock-0.1.0.dist-info/LICENSE
bitblock-0.1.0.dist-info/METADATA
bitblock-0.1.0.dist-info/WHEEL
bitblock-0.1.0.dist-info/top_level.txt
bitblock-0.1.0.dist-info/RECORD
