Metadata-Version: 2.1
Name: bitblock
Version: 0.1.0
Summary: A Bitcoin RPC package for Python with a little bit extra.
Author-email: Charlotte Lockett <lockettc@protonmail.com>
License: GNU GENERAL PUBLIC LICENSE
Project-URL: Homepage, https://github.com/char-lock/bitblock
Project-URL: Bug Tracker, https://github.com/char-lock/bitblock/issues
Classifier: Programming Language :: Python :: 3
Classifier: License :: OSI Approved :: GNU General Public License v3 (GPLv3)
Classifier: Operating System :: OS Independent
Classifier: Development Status :: 2 - Pre-Alpha
Requires-Python: >=3.7
License-File: LICENSE
